graphrole/__init__.py
graphrole/types.py
graphrole/__pycache__/__init__.cpython-37.pyc
graphrole/__pycache__/types.cpython-37.pyc
graphrole/features/__init__.py
graphrole/features/extract.py
graphrole/features/prune.py
graphrole/features/__pycache__/__init__.cpython-37.pyc
graphrole/features/__pycache__/extract.cpython-37.pyc
graphrole/features/__pycache__/prune.cpython-37.pyc
graphrole/graph/__init__.py
graphrole/graph/graph.py
graphrole/graph/__pycache__/__init__.cpython-37.pyc
graphrole/graph/__pycache__/graph.cpython-37.pyc
graphrole/graph/interface/__init__.py
graphrole/graph/interface/base.py
graphrole/graph/interface/igraph.py
graphrole/graph/interface/networkx.py
graphrole/graph/interface/__pycache__/__init__.cpython-37.pyc
graphrole/graph/interface/__pycache__/base.cpython-37.pyc
graphrole/graph/interface/__pycache__/igraph.cpython-37.pyc
graphrole/graph/interface/__pycache__/networkx.cpython-37.pyc
graphrole/roles/__init__.py
graphrole/roles/description_length.py
graphrole/roles/extract.py
graphrole/roles/factor.py
graphrole/roles/__pycache__/__init__.cpython-37.pyc
graphrole/roles/__pycache__/description_length.cpython-37.pyc
graphrole/roles/__pycache__/extract.cpython-37.pyc
graphrole/roles/__pycache__/factor.cpython-37.pyc
tests/__init__.py
tests/__pycache__/__init__.cpython-37.pyc
tests/test_features/__init__.py
tests/test_features/test_extract.py
tests/test_features/test_prune.py
tests/test_features/__pycache__/__init__.cpython-37.pyc
tests/test_features/__pycache__/test_extract.cpython-37.pyc
tests/test_features/__pycache__/test_prune.cpython-37.pyc
tests/test_graph/__init__.py
tests/test_graph/test_graph.py
tests/test_graph/test_interface.py
tests/test_graph/__pycache__/__init__.cpython-37.pyc
tests/test_graph/__pycache__/test_graph.cpython-37.pyc
tests/test_graph/__pycache__/test_interface.cpython-37.pyc
tests/test_roles/__init__.py
tests/test_roles/test_description_length.py
tests/test_roles/test_extract.py
tests/test_roles/test_factor.py
graphrole-1.1.1.dist-info/LICENSE
graphrole-1.1.1.dist-info/METADATA
graphrole-1.1.1.dist-info/WHEEL
graphrole-1.1.1.dist-info/top_level.txt
graphrole-1.1.1.dist-info/RECORD
