Metadata-Version: 2.1
Name: graphrole
Version: 1.1.1
Summary: Automatic feature extraction and node role assignment for transfer learning on graphs
Home-page: https://github.com/dkaslovsky/GraphRole
Author: Daniel Kaslovsky
Author-email: dkaslovsky@gmail.com
License: MIT
Keywords: graph,feature extraction,transfer learning,network,graph analysis,network analysis,refex,rolx
Classifier: Environment :: Console
Classifier: License :: OSI Approved :: MIT License
Classifier: Natural Language :: English
Classifier: Operating System :: OS Independent
Classifier: Programming Language :: Python :: 3.6
Classifier: Programming Language :: Python :: 3.7
Classifier: Programming Language :: Python :: 3.8
Classifier: Programming Language :: Python :: 3.9
Classifier: Programming Language :: Python :: 3.10
Classifier: Programming Language :: Python :: 3.11
License-File: LICENSE
Requires-Dist: networkx (>=3.1)
Requires-Dist: numpy (>=1.24.3)
Requires-Dist: pandas (<2.0)
Requires-Dist: scikit-learn (>=1.3.1)
Requires-Dist: scipy (>=1.11.3)
